{"name":"记笔记","_id":"clq5brktt000iestf6l5w928c","slug":"记笔记","path":"tags/记笔记/","permalink":"http://example.com/tags/%E8%AE%B0%E7%AC%94%E8%AE%B0/","posts":[{"title":"如何高效且优雅做笔记？","date":"2023-12-09T09:02:36.000Z","summary":"优雅，太优雅了","slug":"如何高效且优雅做笔记？","published":true,"updated":"2023-12-14T14:16:03.044Z","_id":"clq5brkts000gestf21yyf4na","layout":"post","photos":[],"link":"","excerpt":"","path":"2023/12/09/如何高效且优雅做笔记？/","permalink":"http://example.com/2023/12/09/%E5%A6%82%E4%BD%95%E9%AB%98%E6%95%88%E4%B8%94%E4%BC%98%E9%9B%85%E5%81%9A%E7%AC%94%E8%AE%B0%EF%BC%9F/","__post":true}],"length":1}